{
  "cli": {
    "version": ">= 10.0.0",
    "appVersionSource": "remote"
  },
  "build": {
    "dev": {
      "developmentClient": true,
      "distribution": "internal",
      "env": {
        "NODE_ENV": "development"
      }
    },
    "dev-sim": {
      "developmentClient": true,
      "distribution": "internal",
      "ios": {
        "simulator": true
      },
      "android": {
        "buildType": "apk"
      },
      "env": {
        "NODE_ENV": "development"
      }
    },
    "preview": {
      "distribution": "internal",
      "android": {
        "buildType": "apk"
      },
      "env": {
        "NODE_ENV": "test"
      }
    },
    "preview:sim": {
      "distribution": "internal",
      "android": {
        "buildType": "apk"
      },
      "env": {
        "NODE_ENV": "test"
      }
    },
    "production": {
      "autoIncrement": true,
      "env": {
        "NODE_ENV": "production"
      }
    }
  },
  "submit": {
    "production": {}
  }
}
